head_pose/__init__.py
head_pose/face.py
head_pose/head_pose_estimator.py
head_pose/model_loader.py
head_pose/utils.py
head_pose/models/model_3D_68.txt
head_pose-0.0.4.dist-info/METADATA
head_pose-0.0.4.dist-info/RECORD
head_pose-0.0.4.dist-info/WHEEL
head_pose-0.0.4.dist-info/top_level.txt
head_pose-0.0.4.dist-info/zip-safe
